{ "button_title": "Smelltu hér til að raunverulegur hljómborð", "button_alt": "Hljómborð tól", "position": "Draga úr hér til stöðu lyklaborðinu sýna", "close_title": "Loka hljómborð tól", "close_alt": "Loka", "backsp": "Bakklykill lykill", "tab": "Tabulator inni", "enter": "Sláðu inn (linefeed) inni", "caps": "Caps Lock takkann", "shift": "Shift takkann", "space": "Space-takkann", "del": "Eyða takkann", "alt": "Varamaður inni", "html": "HTML", "previous_layout": "Fyrri lyklaborði:", "current_layout": "Núverandi lyklaborði:", "next_layout": "Next lyklaborði:", "avail_layout": "Laus skipulag hljómborð", "load_fail": "Áætlunin mistókst að hlaða þarf karakter kortinu file:", "smaller": "Gerðu lyklaborðið almenningur minni", "larger": "Gerðu lyklaborðið almenningur stærri", "key": "Key" }